opendna/__init__.py
opendna/autobahn/__init__.py
opendna/autobahn/repl/__init__.py
opendna/autobahn/repl/_version.py
opendna/autobahn/repl/abc.py
opendna/autobahn/repl/connections.py
opendna/autobahn/repl/mixins.py
opendna/autobahn/repl/pubsub.py
opendna/autobahn/repl/repl.py
opendna/autobahn/repl/rpc.py
opendna/autobahn/repl/sessions.py
opendna/autobahn/repl/utils.py
opendna/autobahn/repl/wamp.py
autobahn_python_repl-18.12.8.dist-info/LICENSE
autobahn_python_repl-18.12.8.dist-info/METADATA
autobahn_python_repl-18.12.8.dist-info/WHEEL
autobahn_python_repl-18.12.8.dist-info/entry_points.txt
autobahn_python_repl-18.12.8.dist-info/top_level.txt
autobahn_python_repl-18.12.8.dist-info/RECORD
