Metadata-Version: 2.1
Name: autobahn-python-repl
Version: 18.12.8
Summary: A REPL interface for interacting with WAMP routers
Home-page: https://github.com/opn-oss/autobahn-python-repl
Author: Adam Jorgensen
Author-email: adam.jorgensen.za@gmail.com
License: MIT
Keywords: autobahn crossbar asyncio repl
Platform: UNKNOWN
Classifier: License :: OSI Approved :: MIT License
Classifier: Development Status :: 4 - Beta
Classifier: Environment :: Console
Classifier: Framework :: AsyncIO
Classifier: Intended Audience :: Developers
Classifier: Operating System :: OS Independent
Classifier: Programming Language :: Python
Classifier: Programming Language :: Python :: 3
Classifier: Programming Language :: Python :: 3.6
Classifier: Programming Language :: Python :: Implementation :: CPython
Classifier: Programming Language :: Python :: Implementation :: PyPy
Classifier: Topic :: Utilities
Requires-Dist: autobahn (>=17.3.1)
Requires-Dist: opn-oss-py-common (>=17.8.4)
Requires-Dist: ptpython (<2.0.1)
Requires-Dist: decorator
